RF_Track.py
_RF_Track.cpython-39-darwin.so
rf_track-2.5.5.dist-info/RECORD
rf_track-2.5.5.dist-info/WHEEL
rf_track-2.5.5.dist-info/top_level.txt
rf_track-2.5.5.dist-info/METADATA
rf_track-2.5.5.dist-info/licenses/LICENSE.md
rf_track.dylibs/libcom_err.3.0.dylib
rf_track.dylibs/libssh2.1.0.1.dylib
rf_track.dylibs/libgsl.28.dylib
rf_track.dylibs/libc++.1.0.dylib
rf_track.dylibs/libssl.3.dylib
rf_track.dylibs/libcrypto.3.dylib
rf_track.dylibs/libgssapi_krb5.2.2.dylib
rf_track.dylibs/libgfortran.5.dylib
rf_track.dylibs/libcblas.3.11.0.dylib
rf_track.dylibs/libz.1.3.1.dylib
rf_track.dylibs/libnghttp2.14.dylib
rf_track.dylibs/libfftw3_threads.3.dylib
rf_track.dylibs/libblas.3.11.0.dylib
rf_track.dylibs/libkrb5.3.3.dylib
rf_track.dylibs/libcurl.4.dylib
rf_track.dylibs/libkrb5support.1.1.dylib
rf_track.dylibs/libk5crypto.3.1.dylib
rf_track.dylibs/libquadmath.0.dylib
rf_track.dylibs/libgcc_s.1.1.dylib
rf_track.dylibs/libfftw3.3.dylib
rf_track.dylibs/libzstd.1.5.7.dylib
